README
imgra.py
setup.py
imgra.egg-info/PKG-INFO
imgra.egg-info/SOURCES.txt
imgra.egg-info/dependency_links.txt
imgra.egg-info/top_level.txt