Metadata-Version: 2.4
Name: imgra
Version: 5
Summary: Image Processing With Graphs
Home-page: https://github.com/mnhrdt/imgra
Author: Enric Meinhardt-Llopis
Author-email: enric.meinhardt@fastmail.com
License: AGPL-3.0
Classifier: Operating System :: OS Independent
Classifier: Topic :: Scientific/Engineering :: Image Processing
Classifier: Topic :: Scientific/Engineering :: Mathematics
Dynamic: author
Dynamic: author-email
Dynamic: classifier
Dynamic: home-page
Dynamic: license
Dynamic: summary
